resumable_sse/__init__.py
resumable_sse/base.py
resumable_sse/factory.py
resumable_sse/memory.py
resumable_sse/redis_stream.py
resumable_sse-0.1.0.dist-info/METADATA
resumable_sse-0.1.0.dist-info/WHEEL
resumable_sse-0.1.0.dist-info/licenses/LICENSE
resumable_sse-0.1.0.dist-info/RECORD
