Metadata-Version: 2.4
Name: resumable-sse
Version: 0.1.0
Summary: Asynchronous recoverable SSE (Server-Sent Events) push toolkit, supporting Redis and in-memory backend.
Project-URL: Repository, https://github.com/vvanglro/resumable-sse
Author-email: vvanglro <vvanglro@gmail.com>
License-Expression: MIT
License-File: LICENSE
Requires-Python: >=3.10
Requires-Dist: redis>=6.2.0
